cxyx_monitor
front
